setup.cfg
setup.py
airplane/airplane.py
airplane/airplanebar.py
airplane.egg-info/PKG-INFO
airplane.egg-info/SOURCES.txt
airplane.egg-info/dependency_links.txt
airplane.egg-info/requires.txt
airplane.egg-info/top_level.txt