Metadata-Version: 1.1
Name: airplane
Version: 0.1
Summary: A little statusbar for Amazon Cloud Drive (http://cloud.amazon.com) on OS X written in Python.
Home-page: https://github.com/C-Codes/Airplane
Author: Christoph Russ
Author-email: chruss@gmx.de
License: MIT
Download-URL: https://github.com/C-Codes/Airplane/tarball/v0.1
Platform: UNKNOWN
Classifier: Development Status :: 3 - Alpha
Classifier: Environment :: MacOS X
Classifier: License :: OSI Approved :: MIT License
Classifier: Natural Language :: English
Classifier: Operating System :: MacOS :: MacOS X
Classifier: Programming Language :: Python :: 2
Classifier: Programming Language :: Python :: 2.7
Classifier: Programming Language :: Python :: 3
Classifier: Programming Language :: Python :: 3.4
